smspider/__init__.py
smspider/s3_sources.py
smspider-0.1.1.dist-info/LICENSE
smspider-0.1.1.dist-info/METADATA
smspider-0.1.1.dist-info/WHEEL
smspider-0.1.1.dist-info/top_level.txt
smspider-0.1.1.dist-info/RECORD
