Metadata-Version: 2.1
Name: smspider
Version: 0.1.1
Summary: SageMaker Spider
Home-page: https://github.com/SuperCowPowers/sagemaker_spider
Author: SuperCowPowers LLC
Author-email: support@supercowpowers.com
License: Apache License 2.0
Keywords: SageMaker,Machine Learning,AWS,Python,Spider
Classifier: Development Status :: 2 - Pre-Alpha
Classifier: Intended Audience :: Developers
Classifier: License :: OSI Approved :: Apache Software License
Classifier: Natural Language :: English
Classifier: Programming Language :: Python :: 3.7
Classifier: Programming Language :: Python :: 3.8
Classifier: Programming Language :: Python :: 3.9
Classifier: Programming Language :: Python :: 3.10
Classifier: Programming Language :: Python :: Implementation :: CPython
Classifier: Programming Language :: Python :: Implementation :: PyPy
License-File: LICENSE
Requires-Dist: sagemaker
